{
	"configurations" : 
	[
		{
			"directories" : 
			[
				{
					"build" : ".",
					"jsonFile" : "directory-.-Debug-f5ebdc15457944623624.json",
					"minimumCMakeVersion" : 
					{
						"string" : "3.0"
					},
					"projectIndex" : 0,
					"source" : ".",
					"targetIndexes" : 
					[
						0,
						1,
						2,
						3
					]
				}
			],
			"name" : "Debug",
			"projects" : 
			[
				{
					"directoryIndexes" : 
					[
						0
					],
					"name" : "tadis",
					"targetIndexes" : 
					[
						0,
						1,
						2,
						3
					]
				}
			],
			"targets" : 
			[
				{
					"directoryIndex" : 0,
					"id" : "lex_test::@6890427a1f51a3e7e1df",
					"jsonFile" : "target-lex_test-Debug-2a0d9b04e2f296b0858f.json",
					"name" : "lex_test",
					"projectIndex" : 0
				},
				{
					"directoryIndex" : 0,
					"id" : "log_test::@6890427a1f51a3e7e1df",
					"jsonFile" : "target-log_test-Debug-4e841891e0f2e5c87a6a.json",
					"name" : "log_test",
					"projectIndex" : 0
				},
				{
					"directoryIndex" : 0,
					"id" : "parse_test::@6890427a1f51a3e7e1df",
					"jsonFile" : "target-parse_test-Debug-161c42022182e4930072.json",
					"name" : "parse_test",
					"projectIndex" : 0
				},
				{
					"directoryIndex" : 0,
					"id" : "tadis::@6890427a1f51a3e7e1df",
					"jsonFile" : "target-tadis-Debug-55b6ffd79066cc7719ee.json",
					"name" : "tadis",
					"projectIndex" : 0
				}
			]
		}
	],
	"kind" : "codemodel",
	"paths" : 
	{
		"build" : "/home/pink/Public/tadis/build",
		"source" : "/home/pink/Public/tadis"
	},
	"version" : 
	{
		"major" : 2,
		"minor" : 3
	}
}
